{
  "type": "FeatureCollection",
  "features": [
    {
      "type": "Feature",
      "geometry": {
        "type": "LineString",
        "coordinates": [
          [30.3141, 59.9343],
          [28.0, 59.0],
          [26.0, 58.0],
          [24.0, 57.0],
          [22.0, 56.0],
          [20.0, 55.0],
          [18.0, 54.5],
          [16.0, 54.2],
          [14.0, 54.0],
          [13.6503, 54.3253]
        ]
      },
      "properties": {
        "name": "Nord Stream 1",
        "type": "gas",
        "operator": "Gazprom",
        "status": "inactive"
      }
    },
    {
      "type": "Feature",
      "geometry": {
        "type": "LineString",
        "coordinates": [
          [30.3141, 59.9343],
          [28.5, 59.2],
          [26.5, 58.3],
          [24.5, 57.3],
          [22.5, 56.3],
          [20.5, 55.3],
          [18.5, 54.7],
          [16.5, 54.4],
          [14.5, 54.2],
          [13.6503, 54.3253]
        ]
      },
      "properties": {
        "name": "Nord Stream 2",
        "type": "gas",
        "operator": "Gazprom",
        "status": "inactive"
      }
    },
    {
      "type": "Feature",
      "geometry": {
        "type": "LineString",
        "coordinates": [
          [37.6173, 55.7558],
          [35.0, 54.0],
          [32.0, 52.5],
          [29.0, 51.5],
          [26.0, 50.5],
          [23.0, 50.0],
          [21.0, 50.3],
          [19.0, 50.8],
          [17.0, 51.2],
          [15.0, 51.5],
          [13.0, 51.8],
          [11.0, 52.0],
          [9.0, 52.3],
          [7.0, 52.5],
          [5.0, 52.4],
          [3.0, 52.2],
          [1.0, 52.0],
          [-1.0, 51.8],
          [-3.0, 51.5],
          [-4.7600, 51.4545]
        ]
      },
      "properties": {
        "name": "Yamal-Europe Pipeline",
        "type": "gas",
        "operator": "Gazprom",
        "status": "active"
      }
    },
    {
      "type": "Feature",
      "geometry": {
        "type": "LineString",
        "coordinates": [
          [55.0, 55.0],
          [52.0, 54.5],
          [49.0, 54.0],
          [46.0, 53.5],
          [43.0, 53.0],
          [40.0, 52.5],
          [37.0, 52.0],
          [34.0, 51.5],
          [31.0, 51.0],
          [28.0, 50.5],
          [25.0, 50.0],
          [22.0, 49.5],
          [19.0, 49.2],
          [16.0, 49.0],
          [14.8037, 50.2660]
        ]
      },
      "properties": {
        "name": "Druzhba Pipeline (Northern Branch)",
        "type": "oil",
        "operator": "Transneft",
        "status": "active"
      }
    },
    {
      "type": "Feature",
      "geometry": {
        "type": "LineString",
        "coordinates": [
          [55.0, 55.0],
          [52.0, 53.0],
          [49.0, 51.5],
          [46.0, 50.5],
          [43.0, 49.5],
          [40.0, 48.8],
          [37.0, 48.5],
          [34.0, 48.3],
          [31.0, 48.0],
          [28.0, 47.8],
          [25.0, 47.5],
          [22.0, 47.3],
          [19.0, 47.2],
          [17.1077, 48.1486]
        ]
      },
      "properties": {
        "name": "Druzhba Pipeline (Southern Branch)",
        "type": "oil",
        "operator": "Transneft",
        "status": "active"
      }
    },
    {
      "type": "Feature",
      "geometry": {
        "type": "LineString",
        "coordinates": [
          [46.7086, 40.4093],
          [45.0, 41.0],
          [43.0, 41.5],
          [41.0, 42.0],
          [39.0, 42.2],
          [37.0, 42.0],
          [35.0, 41.5],
          [33.0, 41.0],
          [31.0, 40.8],
          [29.0, 40.9],
          [28.9784, 41.0082]
        ]
      },
      "properties": {
        "name": "Baku-Tbilisi-Ceyhan Pipeline",
        "type": "oil",
        "operator": "BP/SOCAR",
        "status": "active"
      }
    },
    {
      "type": "Feature",
      "geometry": {
        "type": "LineString",
        "coordinates": [
          [46.7086, 40.4093],
          [45.5, 40.8],
          [44.5, 41.2],
          [43.5, 41.6],
          [42.5, 41.9],
          [41.5, 42.1],
          [40.5, 42.2],
          [39.5, 42.3],
          [38.5, 42.35],
          [37.5, 42.3],
          [36.5, 42.2],
          [35.5, 42.0],
          [34.5, 41.8],
          [33.5, 41.5],
          [32.5, 41.3],
          [31.5, 41.1],
          [30.5, 41.0],
          [29.5, 40.95],
          [28.9784, 41.0082]
        ]
      },
      "properties": {
        "name": "South Caucasus Pipeline",
        "type": "gas",
        "operator": "BP/SOCAR",
        "status": "active"
      }
    },
    {
      "type": "Feature",
      "geometry": {
        "type": "LineString",
        "coordinates": [
          [28.9784, 41.0082],
          [27.0, 40.5],
          [25.0, 40.0],
          [23.0, 39.5],
          [21.0, 39.2],
          [19.0, 39.5],
          [17.0, 40.0],
          [15.8278, 40.8518]
        ]
      },
      "properties": {
        "name": "Trans-Adriatic Pipeline (TAP)",
        "type": "gas",
        "operator": "TAP AG",
        "status": "active"
      }
    },
    {
      "type": "Feature",
      "geometry": {
        "type": "LineString",
        "coordinates": [
          [37.6173, 55.7558],
          [39.0, 54.0],
          [41.0, 52.5],
          [43.0, 51.5],
          [45.0, 50.5],
          [47.0, 49.8],
          [49.0, 49.3],
          [51.0, 48.9],
          [53.0, 48.6],
          [55.0, 48.5],
          [57.0, 48.5],
          [59.0, 48.6],
          [61.0, 48.8],
          [63.0, 49.1],
          [65.0, 49.5],
          [67.0, 50.0],
          [69.0, 50.5],
          [71.0, 51.0],
          [73.0, 51.8],
          [76.8512, 43.2220]
        ]
      },
      "properties": {
        "name": "Central Asia-Center Pipeline",
        "type": "gas",
        "operator": "Gazprom",
        "status": "active"
      }
    },
    {
      "type": "Feature",
      "geometry": {
        "type": "LineString",
        "coordinates": [
          [66.9237, 39.6270],
          [68.0, 40.5],
          [70.0, 41.5],
          [72.0, 42.5],
          [74.0, 43.0],
          [76.0, 43.3],
          [78.0, 43.5],
          [80.0, 43.6],
          [82.0, 43.7],
          [84.0, 43.8],
          [86.0, 43.9],
          [88.0, 44.0],
          [90.0, 44.1],
          [92.0, 43.5],
          [94.0, 42.8],
          [96.0, 42.0],
          [98.0, 41.0],
          [100.0, 40.0],
          [102.0, 39.0],
          [104.0, 38.0],
          [106.0, 37.5],
          [108.0, 37.2],
          [110.0, 37.5],
          [112.0, 38.0],
          [114.0, 38.5],
          [116.4074, 39.9042]
        ]
      },
      "properties": {
        "name": "Central Asia-China Gas Pipeline",
        "type": "gas",
        "operator": "CNPC",
        "status": "active"
      }
    },
    {
      "type": "Feature",
      "geometry": {
        "type": "LineString",
        "coordinates": [
          [95.2796, 21.9162],
          [96.0, 23.0],
          [97.0, 24.0],
          [98.0, 24.5],
          [99.0, 25.0],
          [100.0, 25.3],
          [101.0, 25.5],
          [102.0, 25.6],
          [103.0, 25.7],
          [104.0, 25.8],
          [104.0658, 30.5728]
        ]
      },
      "properties": {
        "name": "China-Myanmar Oil and Gas Pipeline",
        "type": "gas",
        "operator": "CNPC",
        "status": "active"
      }
    },
    {
      "type": "Feature",
      "geometry": {
        "type": "LineString",
        "coordinates": [
          [55.2708, 25.2048],
          [56.0, 26.0],
          [57.0, 27.0],
          [58.0, 28.0],
          [59.0, 29.0],
          [60.0, 30.0],
          [61.0, 31.0],
          [62.0, 32.0],
          [63.0, 33.0],
          [64.0, 34.0],
          [65.0, 34.5],
          [66.0, 35.0],
          [67.0, 35.3],
          [68.0, 35.5],
          [69.0, 35.6],
          [70.0, 35.7],
          [71.0, 35.8],
          [72.0, 35.9],
          [73.0, 36.0],
          [74.0, 36.2],
          [75.0, 36.5],
          [76.0, 37.0],
          [77.0, 37.5],
          [78.0, 38.0],
          [79.0, 38.5],
          [66.9237, 39.6270]
        ]
      },
      "properties": {
        "name": "TAPI Pipeline (Turkmenistan-Afghanistan-Pakistan-India)",
        "type": "gas",
        "operator": "Turkmengaz",
        "status": "planned"
      }
    },
    {
      "type": "Feature",
      "geometry": {
        "type": "LineString",
        "coordinates": [
          [51.1694, 35.6892],
          [50.0, 36.5],
          [49.0, 37.5],
          [48.0, 38.5],
          [47.0, 39.5],
          [46.0, 40.3],
          [45.0, 41.0],
          [44.0, 41.5],
          [43.0, 41.8],
          [42.0, 42.0],
          [41.0, 42.1],
          [40.0, 42.0],
          [39.0, 41.8],
          [38.0, 41.5],
          [37.0, 41.2],
          [36.0, 41.0],
          [35.0, 40.9],
          [34.0, 41.0],
          [33.0, 41.2],
          [32.0, 41.3],
          [31.0, 41.2],
          [30.0, 41.1],
          [29.0, 41.0],
          [28.9784, 41.0082]
        ]
      },
      "properties": {
        "name": "Iran-Turkey Gas Pipeline (Tabriz-Ankara)",
        "type": "gas",
        "operator": "NIGC/BOTAŞ",
        "status": "active"
      }
    },
    {
      "type": "Feature",
      "geometry": {
        "type": "LineString",
        "coordinates": [
          [48.5164, 27.1767],
          [49.0, 28.0],
          [50.0, 29.0],
          [51.0, 30.0],
          [51.5310, 25.2854]
        ]
      },
      "properties": {
        "name": "Saudi-Kuwait Pipeline",
        "type": "oil",
        "operator": "Saudi Aramco",
        "status": "active"
      }
    },
    {
      "type": "Feature",
      "geometry": {
        "type": "LineString",
        "coordinates": [
          [39.1925, 21.5169],
          [40.0, 22.0],
          [41.0, 23.0],
          [42.0, 24.0],
          [43.0, 25.0],
          [44.0, 25.5],
          [45.0, 26.0],
          [46.0, 26.3],
          [47.0, 26.5],
          [48.0, 26.7],
          [49.0, 26.9],
          [50.0, 27.0],
          [50.5577, 26.0667]
        ]
      },
      "properties": {
        "name": "East-West Pipeline (Saudi Arabia)",
        "type": "oil",
        "operator": "Saudi Aramco",
        "status": "active"
      }
    },
    {
      "type": "Feature",
      "geometry": {
        "type": "LineString",
        "coordinates": [
          [32.8597, 24.0889],
          [33.0, 25.0],
          [34.0, 26.0],
          [34.8516, 31.0461]
        ]
      },
      "properties": {
        "name": "Sumed Pipeline (Suez-Mediterranean)",
        "type": "oil",
        "operator": "Arab Petroleum Pipelines Co.",
        "status": "active"
      }
    },
    {
      "type": "Feature",
      "geometry": {
        "type": "LineString",
        "coordinates": [
          [35.2433, 31.7683],
          [34.8516, 31.0461],
          [34.5, 30.5],
          [34.3, 30.0],
          [34.2, 29.5]
        ]
      },
      "properties": {
        "name": "Trans-Israel Pipeline (Eilat-Ashkelon)",
        "type": "oil",
        "operator": "EAPC",
        "status": "active"
      }
    },
    {
      "type": "Feature",
      "geometry": {
        "type": "LineString",
        "coordinates": [
          [18.4241, -33.9249],
          [19.0, -32.0],
          [20.0, -30.0],
          [21.0, -28.0],
          [22.0, -26.0],
          [23.0, -25.0],
          [24.0, -24.5],
          [25.0, -24.2],
          [26.0, -24.0],
          [27.0, -23.9],
          [28.0, -24.0],
          [29.0, -24.2],
          [30.0, -24.5],
          [31.0, -25.0],
          [32.0, -25.5],
          [32.5892, -25.9655]
        ]
      },
      "properties": {
        "name": "Rompco Pipeline (Mozambique-South Africa)",
        "type": "gas",
        "operator": "Sasol/CMH",
        "status": "active"
      }
    },
    {
      "type": "Feature",
      "geometry": {
        "type": "LineString",
        "coordinates": [
          [13.2543, 5.9631],
          [12.0, 7.0],
          [11.0, 8.0],
          [10.0, 9.0],
          [9.0, 10.0],
          [8.0, 11.0],
          [7.0, 11.5],
          [6.0, 12.0],
          [5.0, 12.3],
          [4.0, 12.5],
          [3.0, 12.6],
          [2.0, 12.7],
          [1.0, 12.75],
          [0.0, 12.7],
          [-1.0, 12.6],
          [-2.0, 12.4],
          [-3.0, 12.0],
          [-4.0, 11.5],
          [-5.0, 11.0],
          [-6.0, 10.5],
          [-7.0, 10.0],
          [-8.0, 9.5],
          [-9.0, 9.0],
          [-10.0, 8.5],
          [-11.0, 8.2],
          [-12.0, 8.0],
          [-13.2356, 8.4606]
        ]
      },
      "properties": {
        "name": "West African Gas Pipeline",
        "type": "gas",
        "operator": "WAPCo",
        "status": "active"
      }
    },
    {
      "type": "Feature",
      "geometry": {
        "type": "LineString",
        "coordinates": [
          [3.3792, 6.5244],
          [4.0, 7.0],
          [5.0, 7.5],
          [6.0, 8.0],
          [7.0, 8.3],
          [8.0, 8.5],
          [9.0, 8.6],
          [10.0, 8.7],
          [11.0, 8.8],
          [12.0, 9.0],
          [13.0, 9.2],
          [13.2543, 5.9631]
        ]
      },
      "properties": {
        "name": "Trans-Saharan Gas Pipeline",
        "type": "gas",
        "operator": "NNPC/Sonatrach",
        "status": "planned"
      }
    },
    {
      "type": "Feature",
      "geometry": {
        "type": "LineString",
        "coordinates": [
          [-149.4937, 70.2553],
          [-149.0, 69.5],
          [-148.5, 69.0],
          [-148.0, 68.5],
          [-147.5, 68.0],
          [-147.0, 67.5],
          [-146.5, 67.0],
          [-146.0, 66.5],
          [-145.5, 66.0],
          [-145.0, 65.5],
          [-144.5, 65.0],
          [-144.0, 64.5],
          [-143.5, 64.0],
          [-143.0, 63.5],
          [-142.5, 63.0],
          [-142.0, 62.5],
          [-141.5, 62.0],
          [-141.0, 61.5],
          [-140.5, 61.0],
          [-140.0, 60.5],
          [-139.5, 60.2],
          [-149.9003, 61.2181]
        ]
      },
      "properties": {
        "name": "Trans-Alaska Pipeline System",
        "type": "oil",
        "operator": "Alyeska Pipeline",
        "status": "active"
      }
    },
    {
      "type": "Feature",
      "geometry": {
        "type": "LineString",
        "coordinates": [
          [-110.0687, 56.7267],
          [-109.0, 55.0],
          [-108.0, 54.0],
          [-107.0, 53.0],
          [-106.0, 52.0],
          [-105.0, 51.0],
          [-104.0, 50.5],
          [-103.0, 50.2],
          [-102.0, 50.0],
          [-101.0, 49.8],
          [-100.0, 49.5],
          [-99.0, 49.3],
          [-98.0, 49.0],
          [-97.0, 48.8],
          [-96.0, 48.6],
          [-95.0, 48.4],
          [-94.0, 48.2],
          [-93.0, 48.0],
          [-92.0, 47.8],
          [-91.0, 47.6],
          [-90.0, 47.4],
          [-89.0, 47.2],
          [-88.0, 47.0],
          [-87.0, 46.8],
          [-86.0, 46.6],
          [-85.0, 46.4],
          [-84.0, 46.3],
          [-83.0, 46.2],
          [-82.0, 46.1],
          [-81.0, 46.0],
          [-80.0, 45.9],
          [-79.0, 45.8],
          [-78.0, 45.7],
          [-77.0, 45.6],
          [-76.0, 45.5],
          [-75.0, 45.4],
          [-87.9065, 41.8781]
        ]
      },
      "properties": {
        "name": "Enbridge Pipeline System (Canada to US)",
        "type": "oil",
        "operator": "Enbridge",
        "status": "active"
      }
    },
    {
      "type": "Feature",
      "geometry": {
        "type": "LineString",
        "coordinates": [
          [-110.0687, 56.7267],
          [-109.0, 54.0],
          [-108.0, 52.0],
          [-107.0, 50.5],
          [-106.0, 49.5],
          [-105.0, 48.8],
          [-104.0, 48.3],
          [-103.0, 48.0],
          [-102.0, 47.8],
          [-101.0, 47.6],
          [-100.0, 47.5],
          [-99.0, 47.4],
          [-98.0, 47.3],
          [-97.0, 47.2],
          [-96.0, 47.1],
          [-95.0, 47.0],
          [-94.0, 46.9],
          [-93.0, 46.8],
          [-92.0, 46.7],
          [-91.0, 46.6],
          [-90.0, 46.5],
          [-89.0, 46.0],
          [-88.0, 45.0],
          [-87.0, 44.0],
          [-86.0, 43.0],
          [-85.0, 42.5],
          [-84.0, 42.2],
          [-83.0, 42.0],
          [-95.3698, 29.7604]
        ]
      },
      "properties": {
        "name": "Keystone Pipeline System",
        "type": "oil",
        "operator": "TC Energy",
        "status": "active"
      }
    },
    {
      "type": "Feature",
      "geometry": {
        "type": "LineString",
        "coordinates": [
          [-103.2310, 31.7619],
          [-102.0, 32.0],
          [-101.0, 32.2],
          [-100.0, 32.4],
          [-99.0, 32.5],
          [-98.0, 32.6],
          [-97.0, 32.7],
          [-96.0, 32.8],
          [-95.0, 32.9],
          [-94.0, 33.0],
          [-93.0, 33.1],
          [-92.0, 33.2],
          [-91.0, 33.3],
          [-90.0, 33.4],
          [-89.0, 33.5],
          [-88.0, 33.6],
          [-87.0, 33.7],
          [-86.0, 33.8],
          [-85.0, 33.9],
          [-84.0, 34.0],
          [-83.0, 34.1],
          [-82.0, 34.2],
          [-81.0, 34.3],
          [-80.0, 34.4],
          [-79.0, 34.5],
          [-78.0, 34.6],
          [-77.0, 34.7],
          [-76.6122, 39.2904]
        ]
      },
      "properties": {
        "name": "Colonial Pipeline",
        "type": "oil",
        "operator": "Colonial Pipeline Company",
        "status": "active"
      }
    },
    {
      "type": "Feature",
      "geometry": {
        "type": "LineString",
        "coordinates": [
          [-95.3698, 29.7604],
          [-94.5, 30.0],
          [-94.0, 30.3],
          [-93.5, 30.6],
          [-93.0, 30.9],
          [-92.5, 31.2],
          [-92.0, 31.5],
          [-91.5, 31.8],
          [-91.0, 32.1],
          [-90.5, 32.4],
          [-90.0, 32.7],
          [-89.5, 33.0],
          [-89.0, 33.3],
          [-88.5, 33.6],
          [-88.0, 33.9],
          [-87.5, 34.2],
          [-87.0, 34.5],
          [-86.5, 34.8],
          [-86.0, 35.1],
          [-85.5, 35.4],
          [-85.0, 35.7],
          [-84.5, 36.0],
          [-84.3880, 33.7490]
        ]
      },
      "properties": {
        "name": "Plantation Pipeline",
        "type": "oil",
        "operator": "Kinder Morgan",
        "status": "active"
      }
    },
    {
      "type": "Feature",
      "geometry": {
        "type": "LineString",
        "coordinates": [
          [-118.2437, 34.0522],
          [-117.0, 34.5],
          [-116.0, 35.0],
          [-115.0, 35.5],
          [-114.0, 36.0],
          [-113.0, 36.5],
          [-112.0, 36.8],
          [-111.0, 37.0],
          [-110.0, 37.2],
          [-109.0, 37.3],
          [-108.0, 37.4],
          [-107.0, 37.5],
          [-106.0, 37.6],
          [-105.0, 37.7],
          [-104.9903, 39.7392]
        ]
      },
      "properties": {
        "name": "Rockies Express Pipeline",
        "type": "gas",
        "operator": "Tallgrass Energy",
        "status": "active"
      }
    },
    {
      "type": "Feature",
      "geometry": {
        "type": "LineString",
        "coordinates": [
          [-95.3698, 29.7604],
          [-96.0, 30.5],
          [-97.0, 31.5],
          [-98.0, 32.5],
          [-99.0, 33.5],
          [-100.0, 34.5],
          [-101.0, 35.5],
          [-102.0, 36.5],
          [-103.0, 37.5],
          [-104.0, 38.5],
          [-104.9903, 39.7392]
        ]
      },
      "properties": {
        "name": "Natural Gas Pipeline of America",
        "type": "gas",
        "operator": "Kinder Morgan",
        "status": "active"
      }
    },
    {
      "type": "Feature",
      "geometry": {
        "type": "LineString",
        "coordinates": [
          [-97.7431, 30.2672],
          [-98.0, 31.0],
          [-98.5, 32.0],
          [-99.0, 33.0],
          [-99.5, 34.0],
          [-100.0, 35.0],
          [-100.5, 36.0],
          [-101.0, 37.0],
          [-101.5, 38.0],
          [-102.0, 39.0],
          [-102.5, 40.0],
          [-103.0, 41.0],
          [-103.5, 42.0],
          [-104.0, 43.0],
          [-104.5, 44.0],
          [-105.0, 45.0],
          [-105.5, 46.0],
          [-106.0, 47.0],
          [-106.5, 48.0],
          [-107.0, 48.5],
          [-107.5, 48.8],
          [-108.0, 49.0]
        ]
      },
      "properties": {
        "name": "Northern Border Pipeline",
        "type": "gas",
        "operator": "TC Energy",
        "status": "active"
      }
    },
    {
      "type": "Feature",
      "geometry": {
        "type": "LineString",
        "coordinates": [
          [-100.4867, 25.6866],
          [-99.0, 26.5],
          [-98.0, 27.5],
          [-97.0, 28.5],
          [-96.0, 29.0],
          [-95.3698, 29.7604]
        ]
      },
      "properties": {
        "name": "Sur de Texas-Tuxpan Pipeline",
        "type": "gas",
        "operator": "TC Energy/CFE",
        "status": "active"
      }
    },
    {
      "type": "Feature",
      "geometry": {
        "type": "LineString",
        "coordinates": [
          [-99.1332, 19.4326],
          [-97.0, 20.0],
          [-95.0, 20.5],
          [-93.0, 21.0],
          [-91.0, 21.3],
          [-89.6253, 21.1619]
        ]
      },
      "properties": {
        "name": "Trans-Mexico Gas Pipeline",
        "type": "gas",
        "operator": "TransCanada/CFE",
        "status": "active"
      }
    },
    {
      "type": "Feature",
      "geometry": {
        "type": "LineString",
        "coordinates": [
          [-70.6693, -33.4489],
          [-69.0, -32.0],
          [-68.0, -31.0],
          [-67.0, -30.0],
          [-66.0, -29.5],
          [-65.0, -29.2],
          [-64.0, -29.0],
          [-63.0, -28.9],
          [-62.0, -28.8],
          [-61.0, -28.7],
          [-60.0, -28.6],
          [-59.0, -28.5],
          [-58.0, -28.4],
          [-57.0, -28.3],
          [-56.0, -28.5],
          [-55.0, -29.0],
          [-54.0, -29.5],
          [-53.0, -30.0],
          [-52.0, -30.5],
          [-51.2177, -30.0346]
        ]
      },
      "properties": {
        "name": "Gasoducto GasAndes",
        "type": "gas",
        "operator": "GasAndes",
        "status": "active"
      }
    },
    {
      "type": "Feature",
      "geometry": {
        "type": "LineString",
        "coordinates": [
          [-68.8189, -32.8908],
          [-67.0, -33.5],
          [-65.0, -34.0],
          [-63.0, -34.3],
          [-61.0, -34.5],
          [-59.0, -34.6],
          [-58.3816, -34.6037]
        ]
      },
      "properties": {
        "name": "Gasoducto Transandino (Argentina-Chile)",
        "type": "gas",
        "operator": "TGS/Enap",
        "status": "active"
      }
    },
    {
      "type": "Feature",
      "geometry": {
        "type": "LineString",
        "coordinates": [
          [-43.1729, -22.9068],
          [-44.0, -23.5],
          [-45.0, -24.0],
          [-46.0, -24.3],
          [-47.0, -24.5],
          [-48.0, -24.6],
          [-49.0, -24.7],
          [-50.0, -24.8],
          [-51.0, -24.9],
          [-52.0, -25.0],
          [-53.0, -25.1],
          [-54.0, -25.2],
          [-55.0, -25.3],
          [-56.0, -25.4],
          [-57.0, -25.5],
          [-58.0, -25.6],
          [-59.0, -25.7],
          [-60.0, -25.8],
          [-61.0, -25.9],
          [-62.0, -26.0],
          [-63.0, -26.2],
          [-64.0, -26.5],
          [-65.0, -27.0],
          [-66.0, -27.5],
          [-67.0, -28.0],
          [-68.0, -28.5],
          [-69.0, -29.0],
          [-70.0, -29.5],
          [-70.6693, -33.4489]
        ]
      },
      "properties": {
        "name": "Bolivia-Brazil Gas Pipeline (Gasbol)",
        "type": "gas",
        "operator": "TBG/Petrobras",
        "status": "active"
      }
    },
    {
      "type": "Feature",
      "geometry": {
        "type": "LineString",
        "coordinates": [
          [-72.5000, 7.1250],
          [-71.5, 7.5],
          [-70.5, 8.0],
          [-69.5, 8.5],
          [-68.5, 9.0],
          [-67.5, 9.3],
          [-66.5, 9.5],
          [-65.5, 9.6],
          [-64.5, 9.7],
          [-63.5, 9.75],
          [-62.5, 9.8],
          [-61.5, 9.85],
          [-60.5, 9.9],
          [-59.5, 9.95],
          [-58.9302, 3.9388]
        ]
      },
      "properties": {
        "name": "Venezuela Gas Pipeline",
        "type": "gas",
        "operator": "PDVSA",
        "status": "active"
      }
    }
  ]
}
